qsimbench/__init__.py
qsimbench/py.typed
qsimbench/qsimbench.py
qsimbench-0.1.1.dist-info/METADATA
qsimbench-0.1.1.dist-info/WHEEL
qsimbench-0.1.1.dist-info/licenses/LICENSE
qsimbench-0.1.1.dist-info/RECORD
