Metadata-Version: 2.4
Name: qsimbench
Version: 0.1.1
Summary: QSimBench: An Execution-Level Benchmark Suite for Quantum Software Engineering
Author-email: GBisi <giuseppe.bisicchia@phd.unipi.it>
License-File: LICENSE
Requires-Python: >=3.12
Requires-Dist: ipykernel>=6.30.0
Requires-Dist: requests>=2.32.4
